artemis_common/__init__.py
artemis_common/consts.py
artemis_common/custom_logging.py
artemis_common/exceptions.py
artemis_common/logging.py
artemis_common/token.py
artemis_common/clients/__init__.py
artemis_common/clients/async_client.py
artemis_common/clients/params_model.py
artemis_common/clients/routes.py
artemis_common/config/__init__.py
artemis_common/config/config.py
artemis_common/config/config_loader.py
artemis_common/config/pem.key
artemis_common/config/uvicorn_disable_logging.json
artemis_common/models/__init__.py
artemis_common/models/bases.py
artemis_common/models/jwt.py
artemis_common/models/model_parser.py
artemis_common/models/dal/__init__.py
artemis_common/models/dal/fred.py
artemis_common/models/dal/user_data.py
artemis_common/models/server/__init__.py
artemis_common/models/server/logs.py
artemis_common/models/server/response.py
artemis_common/server/__init__.py
artemis_common/server/exception_handlers.py
artemis_common/server/swagger.py
artemis_common/server/utils.py
artemis_common/server/middlewares/__init__.py
artemis_common/server/middlewares/logging_middleware.py
artemis_common-0.3.7b0.dist-info/METADATA
artemis_common-0.3.7b0.dist-info/WHEEL
artemis_common-0.3.7b0.dist-info/top_level.txt
artemis_common-0.3.7b0.dist-info/RECORD
