Metadata-Version: 2.1
Name: artemis-common
Version: 0.3.7b0
Summary: Artemis common project utilities
Author: 0xArti
Author-email: contact@hunters-of-artemis.com
Requires-Python: >=3.10
Requires-Dist: aiohttp
Requires-Dist: async-lru
Requires-Dist: datadog-api-client
Requires-Dist: ddtrace
Requires-Dist: fastapi (==0.94.1)
Requires-Dist: httpx
Requires-Dist: passlib[bcrypt]
Requires-Dist: pydantic
Requires-Dist: PyJWT
Requires-Dist: python-dateutil
Requires-Dist: python-json-logger
Requires-Dist: pytz
Requires-Dist: requests
Requires-Dist: structlog
Requires-Dist: supertokens-python
Requires-Dist: uvicorn
